mira_sdk_stg/__init__.py
mira_sdk_stg/client.py
mira_sdk_stg/mira/__init__.py
mira_sdk_stg/mira/constants.py
mira_sdk_stg/mira/exceptions.py
mira_sdk_stg/mira/flow.py
mira_sdk_stg/mira/client/__init__.py
mira_sdk_stg/mira/client/async_console.py
mira_sdk_stg/mira/client/async_mira_client.py
mira_sdk_stg/mira/client/console.py
mira_sdk_stg/mira/client/mira_client.py
mira_sdk_stg/mira/models/__init__.py
mira_sdk_stg/mira/models/input.py
mira_sdk_stg/mira/models/metadata.py
mira_sdk_stg/mira/models/model.py
mira_sdk_stg/mira/utils/__init__.py
mira_sdk_stg/mira/utils/util.py
mira_sdk_stg/mira/utils/validation.py
mira_sdk_stg/mira/utils/yaml.py
tests/__init__.py
tests/test_async.py
tests/test_new.py
mira_sdk_stg-0.1.3.dist-info/METADATA
mira_sdk_stg-0.1.3.dist-info/WHEEL
mira_sdk_stg-0.1.3.dist-info/top_level.txt
mira_sdk_stg-0.1.3.dist-info/RECORD
